{
  "indexes": [
    {
      "collectionGroup": "transaction",
      "queryScope": "COLLECTION",
      "fields": [
        {
          "fieldPath": "payload.reconciled",
          "order": "ASCENDING"
        },
        {
          "fieldPath": "payload.void",
          "order": "ASCENDING"
        },
        {
          "fieldPath": "type",
          "order": "ASCENDING"
        },
        {
          "fieldPath": "payload.expiresOn",
          "order": "ASCENDING"
        }
      ]
    },
    {
      "collectionGroup": "transaction",
      "queryScope": "COLLECTION",
      "fields": [
        {
          "fieldPath": "payload.sourceAddress",
          "order": "ASCENDING"
        },
        {
          "fieldPath": "type",
          "order": "ASCENDING"
        },
        {
          "fieldPath": "payload.walletReference.confirmed",
          "order": "ASCENDING"
        },
        {
          "fieldPath": "payload.walletReference.count",
          "order": "ASCENDING"
        }
      ]
    },
    {
      "collectionGroup": "transaction",
      "queryScope": "COLLECTION",
      "fields": [
        {
          "fieldPath": "payload.storageDepositSourceAddress",
          "order": "ASCENDING"
        },
        {
          "fieldPath": "type",
          "order": "ASCENDING"
        },
        {
          "fieldPath": "payload.walletReference.confirmed",
          "order": "ASCENDING"
        },
        {
          "fieldPath": "payload.walletReference.count",
          "order": "ASCENDING"
        }
      ]
    },
    {
      "collectionGroup": "transaction",
      "queryScope": "COLLECTION",
      "fields": [
        {
          "fieldPath": "payload.aliasGovAddress",
          "order": "ASCENDING"
        },
        {
          "fieldPath": "type",
          "order": "ASCENDING"
        },
        {
          "fieldPath": "payload.walletReference.confirmed",
          "order": "ASCENDING"
        },
        {
          "fieldPath": "payload.walletReference.count",
          "order": "ASCENDING"
        }
      ]
    }
  ]
}
